[{"Name":"Bulbasaur","Type 1":"Grass","Type 2":"Poison"},{"Name":"Ivysaur","Type 1":"Grass","Type 2":"Poison"},{"Name":"Venusaur","Type 1":"Grass","Type 2":"Poison"},{"Name":"VenusaurMega Venusaur","Type 1":"Grass","Type 2":"Poison"},{"Name":"Charizard","Type 1":"Fire","Type 2":"Flying"},{"Name":"CharizardMega Charizard X","Type 1":"Fire","Type 2":"Dragon"},{"Name":"CharizardMega Charizard Y","Type 1":"Fire","Type 2":"Flying"},{"Name":"Butterfree","Type 1":"Bug","Type 2":"Flying"},{"Name":"Weedle","Type 1":"Bug","Type 2":"Poison"},{"Name":"Kakuna","Type 1":"Bug","Type 2":"Poison"},{"Name":"Beedrill","Type 1":"Bug","Type 2":"Poison"},{"Name":"BeedrillMega Beedrill","Type 1":"Bug","Type 2":"Poison"},{"Name":"Pidgey","Type 1":"Normal","Type 2":"Flying"},{"Name":"Pidgeotto","Type 1":"Normal","Type 2":"Flying"},{"Name":"Pidgeot","Type 1":"Normal","Type 2":"Flying"},{"Name":"PidgeotMega Pidgeot","Type 1":"Normal","Type 2":"Flying"},{"Name":"Spearow","Type 1":"Normal","Type 2":"Flying"},{"Name":"Fearow","Type 1":"Normal","Type 2":"Flying"},{"Name":"Nidoqueen","Type 1":"Poison","Type 2":"Ground"},{"Name":"Nidoking","Type 1":"Poison","Type 2":"Ground"},{"Name":"Jigglypuff","Type 1":"Normal","Type 2":"Fairy"},{"Name":"Wigglytuff","Type 1":"Normal","Type 2":"Fairy"},{"Name":"Zubat","Type 1":"Poison","Type 2":"Flying"},{"Name":"Golbat","Type 1":"Poison","Type 2":"Flying"},{"Name":"Oddish","Type 1":"Grass","Type 2":"Poison"},{"Name":"Gloom","Type 1":"Grass","Type 2":"Poison"},{"Name":"Vileplume","Type 1":"Grass","Type 2":"Poison"},{"Name":"Paras","Type 1":"Bug","Type 2":"Grass"},{"Name":"Parasect","Type 1":"Bug","Type 2":"Grass"},{"Name":"Venonat","Type 1":"Bug","Type 2":"Poison"},{"Name":"Venomoth","Type 1":"Bug","Type 2":"Poison"},{"Name":"Poliwrath","Type 1":"Water","Type 2":"Fighting"},{"Name":"Bellsprout","Type 1":"Grass","Type 2":"Poison"},{"Name":"Weepinbell","Type 1":"Grass","Type 2":"Poison"},{"Name":"Victreebel","Type 1":"Grass","Type 2":"Poison"},{"Name":"Tentacool","Type 1":"Water","Type 2":"Poison"},{"Name":"Tentacruel","Type 1":"Water","Type 2":"Poison"},{"Name":"Geodude","Type 1":"Rock","Type 2":"Ground"},{"Name":"Graveler","Type 1":"Rock","Type 2":"Ground"},{"Name":"Golem","Type 1":"Rock","Type 2":"Ground"},{"Name":"Slowpoke","Type 1":"Water","Type 2":"Psychic"},{"Name":"Slowbro","Type 1":"Water","Type 2":"Psychic"},{"Name":"SlowbroMega Slowbro","Type 1":"Water","Type 2":"Psychic"},{"Name":"Magnemite","Type 1":"Electric","Type 2":"Steel"},{"Name":"Magneton","Type 1":"Electric","Type 2":"Steel"},{"Name":"Farfetch'd","Type 1":"Normal","Type 2":"Flying"},{"Name":"Doduo","Type 1":"Normal","Type 2":"Flying"},{"Name":"Dodrio","Type 1":"Normal","Type 2":"Flying"},{"Name":"Dewgong","Type 1":"Water","Type 2":"Ice"},{"Name":"Cloyster","Type 1":"Water","Type 2":"Ice"},{"Name":"Gastly","Type 1":"Ghost","Type 2":"Poison"},{"Name":"Haunter","Type 1":"Ghost","Type 2":"Poison"},{"Name":"Gengar","Type 1":"Ghost","Type 2":"Poison"},{"Name":"GengarMega Gengar","Type 1":"Ghost","Type 2":"Poison"},{"Name":"Onix","Type 1":"Rock","Type 2":"Ground"},{"Name":"Exeggcute","Type 1":"Grass","Type 2":"Psychic"},{"Name":"Exeggutor","Type 1":"Grass","Type 2":"Psychic"},{"Name":"Rhyhorn","Type 1":"Ground","Type 2":"Rock"},{"Name":"Rhydon","Type 1":"Ground","Type 2":"Rock"},{"Name":"Starmie","Type 1":"Water","Type 2":"Psychic"},{"Name":"Mr. Mime","Type 1":"Psychic","Type 2":"Fairy"},{"Name":"Scyther","Type 1":"Bug","Type 2":"Flying"},{"Name":"Jynx","Type 1":"Ice","Type 2":"Psychic"},{"Name":"PinsirMega Pinsir","Type 1":"Bug","Type 2":"Flying"},{"Name":"Gyarados","Type 1":"Water","Type 2":"Flying"},{"Name":"GyaradosMega Gyarados","Type 1":"Water","Type 2":"Dark"},{"Name":"Lapras","Type 1":"Water","Type 2":"Ice"},{"Name":"Omanyte","Type 1":"Rock","Type 2":"Water"},{"Name":"Omastar","Type 1":"Rock","Type 2":"Water"},{"Name":"Kabuto","Type 1":"Rock","Type 2":"Water"},{"Name":"Kabutops","Type 1":"Rock","Type 2":"Water"},{"Name":"Aerodactyl","Type 1":"Rock","Type 2":"Flying"},{"Name":"AerodactylMega Aerodactyl","Type 1":"Rock","Type 2":"Flying"},{"Name":"Articuno","Type 1":"Ice","Type 2":"Flying"},{"Name":"Zapdos","Type 1":"Electric","Type 2":"Flying"},{"Name":"Moltres","Type 1":"Fire","Type 2":"Flying"},{"Name":"Dragonite","Type 1":"Dragon","Type 2":"Flying"},{"Name":"MewtwoMega Mewtwo X","Type 1":"Psychic","Type 2":"Fighting"},{"Name":"Hoothoot","Type 1":"Normal","Type 2":"Flying"},{"Name":"Noctowl","Type 1":"Normal","Type 2":"Flying"},{"Name":"Ledyba","Type 1":"Bug","Type 2":"Flying"},{"Name":"Ledian","Type 1":"Bug","Type 2":"Flying"},{"Name":"Spinarak","Type 1":"Bug","Type 2":"Poison"},{"Name":"Ariados","Type 1":"Bug","Type 2":"Poison"},{"Name":"Crobat","Type 1":"Poison","Type 2":"Flying"},{"Name":"Chinchou","Type 1":"Water","Type 2":"Electric"},{"Name":"Lanturn","Type 1":"Water","Type 2":"Electric"},{"Name":"Igglybuff","Type 1":"Normal","Type 2":"Fairy"},{"Name":"Togetic","Type 1":"Fairy","Type 2":"Flying"},{"Name":"Natu","Type 1":"Psychic","Type 2":"Flying"},{"Name":"Xatu","Type 1":"Psychic","Type 2":"Flying"},{"Name":"AmpharosMega Ampharos","Type 1":"Electric","Type 2":"Dragon"},{"Name":"Marill","Type 1":"Water","Type 2":"Fairy"},{"Name":"Azumarill","Type 1":"Water","Type 2":"Fairy"},{"Name":"Hoppip","Type 1":"Grass","Type 2":"Flying"},{"Name":"Skiploom","Type 1":"Grass","Type 2":"Flying"},{"Name":"Jumpluff","Type 1":"Grass","Type 2":"Flying"},{"Name":"Yanma","Type 1":"Bug","Type 2":"Flying"},{"Name":"Wooper","Type 1":"Water","Type 2":"Ground"},{"Name":"Quagsire","Type 1":"Water","Type 2":"Ground"},{"Name":"Murkrow","Type 1":"Dark","Type 2":"Flying"},{"Name":"Slowking","Type 1":"Water","Type 2":"Psychic"},{"Name":"Girafarig","Type 1":"Normal","Type 2":"Psychic"},{"Name":"Forretress","Type 1":"Bug","Type 2":"Steel"},{"Name":"Gligar","Type 1":"Ground","Type 2":"Flying"},{"Name":"Steelix","Type 1":"Steel","Type 2":"Ground"},{"Name":"SteelixMega Steelix","Type 1":"Steel","Type 2":"Ground"},{"Name":"Qwilfish","Type 1":"Water","Type 2":"Poison"},{"Name":"Scizor","Type 1":"Bug","Type 2":"Steel"},{"Name":"ScizorMega Scizor","Type 1":"Bug","Type 2":"Steel"},{"Name":"Shuckle","Type 1":"Bug","Type 2":"Rock"},{"Name":"Heracross","Type 1":"Bug","Type 2":"Fighting"},{"Name":"HeracrossMega Heracross","Type 1":"Bug","Type 2":"Fighting"},{"Name":"Sneasel","Type 1":"Dark","Type 2":"Ice"},{"Name":"Magcargo","Type 1":"Fire","Type 2":"Rock"},{"Name":"Swinub","Type 1":"Ice","Type 2":"Ground"},{"Name":"Piloswine","Type 1":"Ice","Type 2":"Ground"},{"Name":"Corsola","Type 1":"Water","Type 2":"Rock"},{"Name":"Delibird","Type 1":"Ice","Type 2":"Flying"},{"Name":"Mantine","Type 1":"Water","Type 2":"Flying"},{"Name":"Skarmory","Type 1":"Steel","Type 2":"Flying"},{"Name":"Houndour","Type 1":"Dark","Type 2":"Fire"},{"Name":"Houndoom","Type 1":"Dark","Type 2":"Fire"},{"Name":"HoundoomMega Houndoom","Type 1":"Dark","Type 2":"Fire"},{"Name":"Kingdra","Type 1":"Water","Type 2":"Dragon"},{"Name":"Smoochum","Type 1":"Ice","Type 2":"Psychic"},{"Name":"Larvitar","Type 1":"Rock","Type 2":"Ground"},{"Name":"Pupitar","Type 1":"Rock","Type 2":"Ground"},{"Name":"Tyranitar","Type 1":"Rock","Type 2":"Dark"},{"Name":"TyranitarMega Tyranitar","Type 1":"Rock","Type 2":"Dark"},{"Name":"Lugia","Type 1":"Psychic","Type 2":"Flying"},{"Name":"Ho-oh","Type 1":"Fire","Type 2":"Flying"},{"Name":"Celebi","Type 1":"Psychic","Type 2":"Grass"},{"Name":"SceptileMega Sceptile","Type 1":"Grass","Type 2":"Dragon"},{"Name":"Combusken","Type 1":"Fire","Type 2":"Fighting"},{"Name":"Blaziken","Type 1":"Fire","Type 2":"Fighting"},{"Name":"BlazikenMega Blaziken","Type 1":"Fire","Type 2":"Fighting"},{"Name":"Marshtomp","Type 1":"Water","Type 2":"Ground"},{"Name":"Swampert","Type 1":"Water","Type 2":"Ground"},{"Name":"SwampertMega Swampert","Type 1":"Water","Type 2":"Ground"},{"Name":"Beautifly","Type 1":"Bug","Type 2":"Flying"},{"Name":"Dustox","Type 1":"Bug","Type 2":"Poison"},{"Name":"Lotad","Type 1":"Water","Type 2":"Grass"},{"Name":"Lombre","Type 1":"Water","Type 2":"Grass"},{"Name":"Ludicolo","Type 1":"Water","Type 2":"Grass"},{"Name":"Nuzleaf","Type 1":"Grass","Type 2":"Dark"},{"Name":"Shiftry","Type 1":"Grass","Type 2":"Dark"},{"Name":"Taillow","Type 1":"Normal","Type 2":"Flying"},{"Name":"Swellow","Type 1":"Normal","Type 2":"Flying"},{"Name":"Wingull","Type 1":"Water","Type 2":"Flying"},{"Name":"Pelipper","Type 1":"Water","Type 2":"Flying"},{"Name":"Ralts","Type 1":"Psychic","Type 2":"Fairy"},{"Name":"Kirlia","Type 1":"Psychic","Type 2":"Fairy"},{"Name":"Gardevoir","Type 1":"Psychic","Type 2":"Fairy"},{"Name":"GardevoirMega Gardevoir","Type 1":"Psychic","Type 2":"Fairy"},{"Name":"Surskit","Type 1":"Bug","Type 2":"Water"},{"Name":"Masquerain","Type 1":"Bug","Type 2":"Flying"},{"Name":"Breloom","Type 1":"Grass","Type 2":"Fighting"},{"Name":"Nincada","Type 1":"Bug","Type 2":"Ground"},{"Name":"Ninjask","Type 1":"Bug","Type 2":"Flying"},{"Name":"Shedinja","Type 1":"Bug","Type 2":"Ghost"},{"Name":"Azurill","Type 1":"Normal","Type 2":"Fairy"},{"Name":"Sableye","Type 1":"Dark","Type 2":"Ghost"},{"Name":"SableyeMega Sableye","Type 1":"Dark","Type 2":"Ghost"},{"Name":"Mawile","Type 1":"Steel","Type 2":"Fairy"},{"Name":"MawileMega Mawile","Type 1":"Steel","Type 2":"Fairy"},{"Name":"Aron","Type 1":"Steel","Type 2":"Rock"},{"Name":"Lairon","Type 1":"Steel","Type 2":"Rock"},{"Name":"Aggron","Type 1":"Steel","Type 2":"Rock"},{"Name":"Meditite","Type 1":"Fighting","Type 2":"Psychic"},{"Name":"Medicham","Type 1":"Fighting","Type 2":"Psychic"},{"Name":"MedichamMega Medicham","Type 1":"Fighting","Type 2":"Psychic"},{"Name":"Roselia","Type 1":"Grass","Type 2":"Poison"},{"Name":"Carvanha","Type 1":"Water","Type 2":"Dark"},{"Name":"Sharpedo","Type 1":"Water","Type 2":"Dark"},{"Name":"SharpedoMega Sharpedo","Type 1":"Water","Type 2":"Dark"},{"Name":"Numel","Type 1":"Fire","Type 2":"Ground"},{"Name":"Camerupt","Type 1":"Fire","Type 2":"Ground"},{"Name":"CameruptMega Camerupt","Type 1":"Fire","Type 2":"Ground"},{"Name":"Vibrava","Type 1":"Ground","Type 2":"Dragon"},{"Name":"Flygon","Type 1":"Ground","Type 2":"Dragon"},{"Name":"Cacturne","Type 1":"Grass","Type 2":"Dark"},{"Name":"Swablu","Type 1":"Normal","Type 2":"Flying"},{"Name":"Altaria","Type 1":"Dragon","Type 2":"Flying"},{"Name":"AltariaMega Altaria","Type 1":"Dragon","Type 2":"Fairy"},{"Name":"Lunatone","Type 1":"Rock","Type 2":"Psychic"},{"Name":"Solrock","Type 1":"Rock","Type 2":"Psychic"},{"Name":"Barboach","Type 1":"Water","Type 2":"Ground"},{"Name":"Whiscash","Type 1":"Water","Type 2":"Ground"},{"Name":"Crawdaunt","Type 1":"Water","Type 2":"Dark"},{"Name":"Baltoy","Type 1":"Ground","Type 2":"Psychic"},{"Name":"Claydol","Type 1":"Ground","Type 2":"Psychic"},{"Name":"Lileep","Type 1":"Rock","Type 2":"Grass"},{"Name":"Cradily","Type 1":"Rock","Type 2":"Grass"},{"Name":"Anorith","Type 1":"Rock","Type 2":"Bug"},{"Name":"Armaldo","Type 1":"Rock","Type 2":"Bug"},{"Name":"Tropius","Type 1":"Grass","Type 2":"Flying"},{"Name":"Spheal","Type 1":"Ice","Type 2":"Water"},{"Name":"Sealeo","Type 1":"Ice","Type 2":"Water"},{"Name":"Walrein","Type 1":"Ice","Type 2":"Water"},{"Name":"Relicanth","Type 1":"Water","Type 2":"Rock"},{"Name":"Salamence","Type 1":"Dragon","Type 2":"Flying"},{"Name":"SalamenceMega Salamence","Type 1":"Dragon","Type 2":"Flying"},{"Name":"Beldum","Type 1":"Steel","Type 2":"Psychic"},{"Name":"Metang","Type 1":"Steel","Type 2":"Psychic"},{"Name":"Metagross","Type 1":"Steel","Type 2":"Psychic"},{"Name":"MetagrossMega Metagross","Type 1":"Steel","Type 2":"Psychic"},{"Name":"Latias","Type 1":"Dragon","Type 2":"Psychic"},{"Name":"LatiasMega Latias","Type 1":"Dragon","Type 2":"Psychic"},{"Name":"Latios","Type 1":"Dragon","Type 2":"Psychic"},{"Name":"LatiosMega Latios","Type 1":"Dragon","Type 2":"Psychic"},{"Name":"GroudonPrimal Groudon","Type 1":"Ground","Type 2":"Fire"},{"Name":"Rayquaza","Type 1":"Dragon","Type 2":"Flying"},{"Name":"RayquazaMega Rayquaza","Type 1":"Dragon","Type 2":"Flying"},{"Name":"Jirachi","Type 1":"Steel","Type 2":"Psychic"},{"Name":"Torterra","Type 1":"Grass","Type 2":"Ground"},{"Name":"Monferno","Type 1":"Fire","Type 2":"Fighting"},{"Name":"Infernape","Type 1":"Fire","Type 2":"Fighting"},{"Name":"Empoleon","Type 1":"Water","Type 2":"Steel"},{"Name":"Starly","Type 1":"Normal","Type 2":"Flying"},{"Name":"Staravia","Type 1":"Normal","Type 2":"Flying"},{"Name":"Staraptor","Type 1":"Normal","Type 2":"Flying"},{"Name":"Bibarel","Type 1":"Normal","Type 2":"Water"},{"Name":"Budew","Type 1":"Grass","Type 2":"Poison"},{"Name":"Roserade","Type 1":"Grass","Type 2":"Poison"},{"Name":"Shieldon","Type 1":"Rock","Type 2":"Steel"},{"Name":"Bastiodon","Type 1":"Rock","Type 2":"Steel"},{"Name":"WormadamPlant Cloak","Type 1":"Bug","Type 2":"Grass"},{"Name":"WormadamSandy Cloak","Type 1":"Bug","Type 2":"Ground"},{"Name":"WormadamTrash Cloak","Type 1":"Bug","Type 2":"Steel"},{"Name":"Mothim","Type 1":"Bug","Type 2":"Flying"},{"Name":"Combee","Type 1":"Bug","Type 2":"Flying"},{"Name":"Vespiquen","Type 1":"Bug","Type 2":"Flying"},{"Name":"Gastrodon","Type 1":"Water","Type 2":"Ground"},{"Name":"Drifloon","Type 1":"Ghost","Type 2":"Flying"},{"Name":"Drifblim","Type 1":"Ghost","Type 2":"Flying"},{"Name":"LopunnyMega Lopunny","Type 1":"Normal","Type 2":"Fighting"},{"Name":"Honchkrow","Type 1":"Dark","Type 2":"Flying"},{"Name":"Stunky","Type 1":"Poison","Type 2":"Dark"},{"Name":"Skuntank","Type 1":"Poison","Type 2":"Dark"},{"Name":"Bronzor","Type 1":"Steel","Type 2":"Psychic"},{"Name":"Bronzong","Type 1":"Steel","Type 2":"Psychic"},{"Name":"Mime Jr.","Type 1":"Psychic","Type 2":"Fairy"},{"Name":"Chatot","Type 1":"Normal","Type 2":"Flying"},{"Name":"Spiritomb","Type 1":"Ghost","Type 2":"Dark"},{"Name":"Gible","Type 1":"Dragon","Type 2":"Ground"},{"Name":"Gabite","Type 1":"Dragon","Type 2":"Ground"},{"Name":"Garchomp","Type 1":"Dragon","Type 2":"Ground"},{"Name":"GarchompMega Garchomp","Type 1":"Dragon","Type 2":"Ground"},{"Name":"Lucario","Type 1":"Fighting","Type 2":"Steel"},{"Name":"LucarioMega Lucario","Type 1":"Fighting","Type 2":"Steel"},{"Name":"Skorupi","Type 1":"Poison","Type 2":"Bug"},{"Name":"Drapion","Type 1":"Poison","Type 2":"Dark"},{"Name":"Croagunk","Type 1":"Poison","Type 2":"Fighting"},{"Name":"Toxicroak","Type 1":"Poison","Type 2":"Fighting"},{"Name":"Mantyke","Type 1":"Water","Type 2":"Flying"},{"Name":"Snover","Type 1":"Grass","Type 2":"Ice"},{"Name":"Abomasnow","Type 1":"Grass","Type 2":"Ice"},{"Name":"AbomasnowMega Abomasnow","Type 1":"Grass","Type 2":"Ice"},{"Name":"Weavile","Type 1":"Dark","Type 2":"Ice"},{"Name":"Magnezone","Type 1":"Electric","Type 2":"Steel"},{"Name":"Rhyperior","Type 1":"Ground","Type 2":"Rock"},{"Name":"Togekiss","Type 1":"Fairy","Type 2":"Flying"},{"Name":"Yanmega","Type 1":"Bug","Type 2":"Flying"},{"Name":"Gliscor","Type 1":"Ground","Type 2":"Flying"},{"Name":"Mamoswine","Type 1":"Ice","Type 2":"Ground"},{"Name":"Gallade","Type 1":"Psychic","Type 2":"Fighting"},{"Name":"GalladeMega Gallade","Type 1":"Psychic","Type 2":"Fighting"},{"Name":"Probopass","Type 1":"Rock","Type 2":"Steel"},{"Name":"Froslass","Type 1":"Ice","Type 2":"Ghost"},{"Name":"Rotom","Type 1":"Electric","Type 2":"Ghost"},{"Name":"RotomHeat Rotom","Type 1":"Electric","Type 2":"Fire"},{"Name":"RotomWash Rotom","Type 1":"Electric","Type 2":"Water"},{"Name":"RotomFrost Rotom","Type 1":"Electric","Type 2":"Ice"},{"Name":"RotomFan Rotom","Type 1":"Electric","Type 2":"Flying"},{"Name":"RotomMow Rotom","Type 1":"Electric","Type 2":"Grass"},{"Name":"Dialga","Type 1":"Steel","Type 2":"Dragon"},{"Name":"Palkia","Type 1":"Water","Type 2":"Dragon"},{"Name":"Heatran","Type 1":"Fire","Type 2":"Steel"},{"Name":"GiratinaAltered Forme","Type 1":"Ghost","Type 2":"Dragon"},{"Name":"GiratinaOrigin Forme","Type 1":"Ghost","Type 2":"Dragon"},{"Name":"ShayminSky Forme","Type 1":"Grass","Type 2":"Flying"},{"Name":"Victini","Type 1":"Psychic","Type 2":"Fire"},{"Name":"Pignite","Type 1":"Fire","Type 2":"Fighting"},{"Name":"Emboar","Type 1":"Fire","Type 2":"Fighting"},{"Name":"Pidove","Type 1":"Normal","Type 2":"Flying"},{"Name":"Tranquill","Type 1":"Normal","Type 2":"Flying"},{"Name":"Unfezant","Type 1":"Normal","Type 2":"Flying"},{"Name":"Woobat","Type 1":"Psychic","Type 2":"Flying"},{"Name":"Swoobat","Type 1":"Psychic","Type 2":"Flying"},{"Name":"Excadrill","Type 1":"Ground","Type 2":"Steel"},{"Name":"AudinoMega Audino","Type 1":"Normal","Type 2":"Fairy"},{"Name":"Palpitoad","Type 1":"Water","Type 2":"Ground"},{"Name":"Seismitoad","Type 1":"Water","Type 2":"Ground"},{"Name":"Sewaddle","Type 1":"Bug","Type 2":"Grass"},{"Name":"Swadloon","Type 1":"Bug","Type 2":"Grass"},{"Name":"Leavanny","Type 1":"Bug","Type 2":"Grass"},{"Name":"Venipede","Type 1":"Bug","Type 2":"Poison"},{"Name":"Whirlipede","Type 1":"Bug","Type 2":"Poison"},{"Name":"Scolipede","Type 1":"Bug","Type 2":"Poison"},{"Name":"Cottonee","Type 1":"Grass","Type 2":"Fairy"},{"Name":"Whimsicott","Type 1":"Grass","Type 2":"Fairy"},{"Name":"Sandile","Type 1":"Ground","Type 2":"Dark"},{"Name":"Krokorok","Type 1":"Ground","Type 2":"Dark"},{"Name":"Krookodile","Type 1":"Ground","Type 2":"Dark"},{"Name":"DarmanitanZen Mode","Type 1":"Fire","Type 2":"Psychic"},{"Name":"Dwebble","Type 1":"Bug","Type 2":"Rock"},{"Name":"Crustle","Type 1":"Bug","Type 2":"Rock"},{"Name":"Scraggy","Type 1":"Dark","Type 2":"Fighting"},{"Name":"Scrafty","Type 1":"Dark","Type 2":"Fighting"},{"Name":"Sigilyph","Type 1":"Psychic","Type 2":"Flying"},{"Name":"Tirtouga","Type 1":"Water","Type 2":"Rock"},{"Name":"Carracosta","Type 1":"Water","Type 2":"Rock"},{"Name":"Archen","Type 1":"Rock","Type 2":"Flying"},{"Name":"Archeops","Type 1":"Rock","Type 2":"Flying"},{"Name":"Ducklett","Type 1":"Water","Type 2":"Flying"},{"Name":"Swanna","Type 1":"Water","Type 2":"Flying"},{"Name":"Deerling","Type 1":"Normal","Type 2":"Grass"},{"Name":"Sawsbuck","Type 1":"Normal","Type 2":"Grass"},{"Name":"Emolga","Type 1":"Electric","Type 2":"Flying"},{"Name":"Escavalier","Type 1":"Bug","Type 2":"Steel"},{"Name":"Foongus","Type 1":"Grass","Type 2":"Poison"},{"Name":"Amoonguss","Type 1":"Grass","Type 2":"Poison"},{"Name":"Frillish","Type 1":"Water","Type 2":"Ghost"},{"Name":"Jellicent","Type 1":"Water","Type 2":"Ghost"},{"Name":"Joltik","Type 1":"Bug","Type 2":"Electric"},{"Name":"Galvantula","Type 1":"Bug","Type 2":"Electric"},{"Name":"Ferroseed","Type 1":"Grass","Type 2":"Steel"},{"Name":"Ferrothorn","Type 1":"Grass","Type 2":"Steel"},{"Name":"Litwick","Type 1":"Ghost","Type 2":"Fire"},{"Name":"Lampent","Type 1":"Ghost","Type 2":"Fire"},{"Name":"Chandelure","Type 1":"Ghost","Type 2":"Fire"},{"Name":"Stunfisk","Type 1":"Ground","Type 2":"Electric"},{"Name":"Golett","Type 1":"Ground","Type 2":"Ghost"},{"Name":"Golurk","Type 1":"Ground","Type 2":"Ghost"},{"Name":"Pawniard","Type 1":"Dark","Type 2":"Steel"},{"Name":"Bisharp","Type 1":"Dark","Type 2":"Steel"},{"Name":"Rufflet","Type 1":"Normal","Type 2":"Flying"},{"Name":"Braviary","Type 1":"Normal","Type 2":"Flying"},{"Name":"Vullaby","Type 1":"Dark","Type 2":"Flying"},{"Name":"Mandibuzz","Type 1":"Dark","Type 2":"Flying"},{"Name":"Durant","Type 1":"Bug","Type 2":"Steel"},{"Name":"Deino","Type 1":"Dark","Type 2":"Dragon"},{"Name":"Zweilous","Type 1":"Dark","Type 2":"Dragon"},{"Name":"Hydreigon","Type 1":"Dark","Type 2":"Dragon"},{"Name":"Larvesta","Type 1":"Bug","Type 2":"Fire"},{"Name":"Volcarona","Type 1":"Bug","Type 2":"Fire"},{"Name":"Cobalion","Type 1":"Steel","Type 2":"Fighting"},{"Name":"Terrakion","Type 1":"Rock","Type 2":"Fighting"},{"Name":"Virizion","Type 1":"Grass","Type 2":"Fighting"},{"Name":"ThundurusIncarnate Forme","Type 1":"Electric","Type 2":"Flying"},{"Name":"ThundurusTherian Forme","Type 1":"Electric","Type 2":"Flying"},{"Name":"Reshiram","Type 1":"Dragon","Type 2":"Fire"},{"Name":"Zekrom","Type 1":"Dragon","Type 2":"Electric"},{"Name":"LandorusIncarnate Forme","Type 1":"Ground","Type 2":"Flying"},{"Name":"LandorusTherian Forme","Type 1":"Ground","Type 2":"Flying"},{"Name":"Kyurem","Type 1":"Dragon","Type 2":"Ice"},{"Name":"KyuremBlack Kyurem","Type 1":"Dragon","Type 2":"Ice"},{"Name":"KyuremWhite Kyurem","Type 1":"Dragon","Type 2":"Ice"},{"Name":"KeldeoOrdinary Forme","Type 1":"Water","Type 2":"Fighting"},{"Name":"KeldeoResolute Forme","Type 1":"Water","Type 2":"Fighting"},{"Name":"MeloettaAria Forme","Type 1":"Normal","Type 2":"Psychic"},{"Name":"MeloettaPirouette Forme","Type 1":"Normal","Type 2":"Fighting"},{"Name":"Genesect","Type 1":"Bug","Type 2":"Steel"},{"Name":"Chesnaught","Type 1":"Grass","Type 2":"Fighting"},{"Name":"Delphox","Type 1":"Fire","Type 2":"Psychic"},{"Name":"Greninja","Type 1":"Water","Type 2":"Dark"},{"Name":"Diggersby","Type 1":"Normal","Type 2":"Ground"},{"Name":"Fletchling","Type 1":"Normal","Type 2":"Flying"},{"Name":"Fletchinder","Type 1":"Fire","Type 2":"Flying"},{"Name":"Talonflame","Type 1":"Fire","Type 2":"Flying"},{"Name":"Vivillon","Type 1":"Bug","Type 2":"Flying"},{"Name":"Litleo","Type 1":"Fire","Type 2":"Normal"},{"Name":"Pyroar","Type 1":"Fire","Type 2":"Normal"},{"Name":"Pangoro","Type 1":"Fighting","Type 2":"Dark"},{"Name":"Honedge","Type 1":"Steel","Type 2":"Ghost"},{"Name":"Doublade","Type 1":"Steel","Type 2":"Ghost"},{"Name":"AegislashBlade Forme","Type 1":"Steel","Type 2":"Ghost"},{"Name":"AegislashShield Forme","Type 1":"Steel","Type 2":"Ghost"},{"Name":"Inkay","Type 1":"Dark","Type 2":"Psychic"},{"Name":"Malamar","Type 1":"Dark","Type 2":"Psychic"},{"Name":"Binacle","Type 1":"Rock","Type 2":"Water"},{"Name":"Barbaracle","Type 1":"Rock","Type 2":"Water"},{"Name":"Skrelp","Type 1":"Poison","Type 2":"Water"},{"Name":"Dragalge","Type 1":"Poison","Type 2":"Dragon"},{"Name":"Helioptile","Type 1":"Electric","Type 2":"Normal"},{"Name":"Heliolisk","Type 1":"Electric","Type 2":"Normal"},{"Name":"Tyrunt","Type 1":"Rock","Type 2":"Dragon"},{"Name":"Tyrantrum","Type 1":"Rock","Type 2":"Dragon"},{"Name":"Amaura","Type 1":"Rock","Type 2":"Ice"},{"Name":"Aurorus","Type 1":"Rock","Type 2":"Ice"},{"Name":"Hawlucha","Type 1":"Fighting","Type 2":"Flying"},{"Name":"Dedenne","Type 1":"Electric","Type 2":"Fairy"},{"Name":"Carbink","Type 1":"Rock","Type 2":"Fairy"},{"Name":"Klefki","Type 1":"Steel","Type 2":"Fairy"},{"Name":"Phantump","Type 1":"Ghost","Type 2":"Grass"},{"Name":"Trevenant","Type 1":"Ghost","Type 2":"Grass"},{"Name":"PumpkabooAverage Size","Type 1":"Ghost","Type 2":"Grass"},{"Name":"PumpkabooSmall Size","Type 1":"Ghost","Type 2":"Grass"},{"Name":"PumpkabooLarge Size","Type 1":"Ghost","Type 2":"Grass"},{"Name":"PumpkabooSuper Size","Type 1":"Ghost","Type 2":"Grass"},{"Name":"GourgeistAverage Size","Type 1":"Ghost","Type 2":"Grass"},{"Name":"GourgeistSmall Size","Type 1":"Ghost","Type 2":"Grass"},{"Name":"GourgeistLarge Size","Type 1":"Ghost","Type 2":"Grass"},{"Name":"GourgeistSuper Size","Type 1":"Ghost","Type 2":"Grass"},{"Name":"Noibat","Type 1":"Flying","Type 2":"Dragon"},{"Name":"Noivern","Type 1":"Flying","Type 2":"Dragon"},{"Name":"Yveltal","Type 1":"Dark","Type 2":"Flying"},{"Name":"Zygarde50% Forme","Type 1":"Dragon","Type 2":"Ground"},{"Name":"Diancie","Type 1":"Rock","Type 2":"Fairy"},{"Name":"DiancieMega Diancie","Type 1":"Rock","Type 2":"Fairy"},{"Name":"HoopaHoopa Confined","Type 1":"Psychic","Type 2":"Ghost"},{"Name":"HoopaHoopa Unbound","Type 1":"Psychic","Type 2":"Dark"},{"Name":"Volcanion","Type 1":"Fire","Type 2":"Water"}]